{"basics":{"name":"Clément Cabot","label":"Energy Economist","image":"","email":"","phone":"","url":"https://clementcabot.github.io/","summary":"PhD in Energy Economics, CentraleSupélec Engineer.","location":{"address":"","postalCode":"75005","city":"Paris","countryCode":"FR","region":""},"profiles":[{"network":"LinkedIn","username":"clementcabot","url":"https://www.linkedin.com/in/clementcabot/"}]},"work":[{"name":"Deloitte","position":"Manager","url":"","startDate":"2022-01-01","endDate":"2024-01-01","summary":"Direct supervision of 2-5 team members. In charge of client engagment (200€ to 1M€). Expert for audit team, regulatory analysis, techno-economic assessment","highlights":["Management"]},{"name":"Deloitte","position":"Energy Economist","url":"","startDate":"2018-01-01","endDate":"2024-01-01","summary":"Senior energy economist, Manager. Extensive experiences in the energy and climate field","highlights":["Economy"]},{"name":"RTE","position":"Research Engineer","url":"","startDate":"2017-01-01","endDate":"2018-01-01","summary":"Analysis of the impact of the new market regulations and power mix. Developped a EU frequency model","highlights":["Economy"]}],"education":[{"institution":"Ecole des Mines","location":"Paris, France","url":"https://www.minesparis.psl.eu/","area":"CERNA, Centre d'économie industrielle ","studyType":"PhD","startDate":"2019-01-01","endDate":"2023-01-01"},{"institution":"CentraleSupléec","location":"Paris, France","url":"https://www.centralesupelec.fr/en","area":"Energy, Computer Science","studyType":"MSc","startDate":"2014-01-01","endDate":"2018-01-01"}],"skills":[{"name":"Energy Economics","level":"Master","icon":"fa-solid fa-hashtag","keywords":["Market design","Industrial decarbonisation","Power systems"]}],"languages":[{"language":"French","fluency":"Native speaker","icon":""},{"language":"English","fluency":"Fluent","icon":""}],"interests":[{"name":"Outdoors","icon":"fa-solid fa-tag","keywords":["Climbing","Trail","Cycling"]}]}